intelmq/__init__.py
intelmq/bots/__init__.py
intelmq/bots/experts/__init__.py
intelmq/bots/experts/certbund_contact/__init__.py
intelmq/bots/experts/certbund_contact/expert.py
intelmq/bots/experts/certbund_rules/__init__.py
intelmq/bots/experts/certbund_rules/expert.py
intelmq_certbund_contact/__init__.py
intelmq_certbund_contact/annotations.py
intelmq_certbund_contact/common.py
intelmq_certbund_contact/eventjson.py
intelmq_certbund_contact/rulesupport.py
intelmq_certbund_contact/ripe/__init__.py
intelmq_certbund_contact/ripe/ripe_data.py
intelmq_certbund_contact/ripe/ripe_diff.py
intelmq_certbund_contact/ripe/ripe_import.py
intelmq_certbund_contact-0.9.8.data/scripts/import-national-certs
intelmq_certbund_contact-0.9.8.data/scripts/ripe_download
tests/__init__.py
tests/create_email_tag_cases.py
tests/certbund_contact/__init__.py
tests/certbund_contact/test_annotations.py
tests/certbund_contact/test_expert.py
tests/certbund_contact/test_rules.py
intelmq_certbund_contact-0.9.8.dist-info/LICENSE
intelmq_certbund_contact-0.9.8.dist-info/METADATA
intelmq_certbund_contact-0.9.8.dist-info/WHEEL
intelmq_certbund_contact-0.9.8.dist-info/entry_points.txt
intelmq_certbund_contact-0.9.8.dist-info/top_level.txt
intelmq_certbund_contact-0.9.8.dist-info/RECORD
