Metadata-Version: 2.1
Name: intelmq-certbund-contact
Version: 0.9.8
Summary: IntelMQ Contacts is a contact database for IntelMQ with related expert bots
Home-page: https://github.com/Intevation/intelmq-certbund-contact
Author: Intevation GmbH
Maintainer: Intevation GmbH
Maintainer-email: sebastian.wagner@intevation.de
License: AGPL-3.0-or-later
Requires-Python: >=3.4
License-File: LICENSE
Requires-Dist: intelmq (>=3.0.2)
Requires-Dist: intelmqmail
Requires-Dist: psycopg2
